moderation_api/__init__.py
moderation_api/_base_client.py
moderation_api/_client.py
moderation_api/_compat.py
moderation_api/_constants.py
moderation_api/_exceptions.py
moderation_api/_files.py
moderation_api/_models.py
moderation_api/_qs.py
moderation_api/_resource.py
moderation_api/_response.py
moderation_api/_streaming.py
moderation_api/_types.py
moderation_api/_version.py
moderation_api/py.typed
moderation_api/_utils/__init__.py
moderation_api/_utils/_compat.py
moderation_api/_utils/_datetime_parse.py
moderation_api/_utils/_json.py
moderation_api/_utils/_logs.py
moderation_api/_utils/_proxy.py
moderation_api/_utils/_reflection.py
moderation_api/_utils/_resources_proxy.py
moderation_api/_utils/_streams.py
moderation_api/_utils/_sync.py
moderation_api/_utils/_transform.py
moderation_api/_utils/_typing.py
moderation_api/_utils/_utils.py
moderation_api/lib/.keep
moderation_api/resources/__init__.py
moderation_api/resources/account.py
moderation_api/resources/auth.py
moderation_api/resources/authors.py
moderation_api/resources/content.py
moderation_api/resources/actions/__init__.py
moderation_api/resources/actions/actions.py
moderation_api/resources/actions/execute.py
moderation_api/resources/queue/__init__.py
moderation_api/resources/queue/items.py
moderation_api/resources/queue/queue.py
moderation_api/resources/wordlist/__init__.py
moderation_api/resources/wordlist/wordlist.py
moderation_api/resources/wordlist/words.py
moderation_api/types/__init__.py
moderation_api/types/account_list_response.py
moderation_api/types/action_create_params.py
moderation_api/types/action_create_response.py
moderation_api/types/action_delete_response.py
moderation_api/types/action_list_params.py
moderation_api/types/action_list_response.py
moderation_api/types/action_retrieve_response.py
moderation_api/types/action_update_params.py
moderation_api/types/action_update_response.py
moderation_api/types/auth_create_response.py
moderation_api/types/auth_retrieve_response.py
moderation_api-1.7.0.dist-info/METADATA
moderation_api-1.7.0.dist-info/WHEEL
moderation_api-1.7.0.dist-info/licenses/LICENSE
moderation_api-1.7.0.dist-info/RECORD
